vectorforge/__init__.py
vectorforge/canon.py
vectorforge/client.py
vectorforge/types.py
vectorforgeai-0.1.1.dist-info/METADATA
vectorforgeai-0.1.1.dist-info/WHEEL
vectorforgeai-0.1.1.dist-info/RECORD
