Metadata-Version: 2.4
Name: vectorforgeai
Version: 0.1.1
Summary: Official Python SDK for VectorForge Cloud APIs
Project-URL: Homepage, https://vectorforge.ai
Project-URL: Documentation, https://docs.vectorforge.ai
Project-URL: Repository, https://github.com/VectorForgeAI/API
Project-URL: Issues, https://github.com/VectorForgeAI/API/issues
Author-email: VectorForge <support@vectorforge.ai>
License: MIT
Keywords: ai,cryptography,divt,integrity,receipts,vectorforge,verification
Classifier: Development Status :: 3 - Alpha
Classifier: Intended Audience :: Developers
Classifier: License :: OSI Approved :: MIT License
Classifier: Programming Language :: Python :: 3
Classifier: Programming Language :: Python :: 3.9
Classifier: Programming Language :: Python :: 3.10
Classifier: Programming Language :: Python :: 3.11
Classifier: Programming Language :: Python :: 3.12
Classifier: Topic :: Software Development :: Libraries :: Python Modules
Requires-Python: >=3.9
Requires-Dist: requests>=2.28.0
Provides-Extra: dev
Requires-Dist: black>=23.0.0; extra == 'dev'
Requires-Dist: mypy>=1.0.0; extra == 'dev'
Requires-Dist: pytest>=7.0.0; extra == 'dev'
Requires-Dist: ruff>=0.1.0; extra == 'dev'
Provides-Extra: image
Requires-Dist: pillow>=10.0.0; extra == 'image'
